pydistinct/__init__.py
pydistinct/bootstrap.py
pydistinct/ensemble_estimators.py
pydistinct/sampling.py
pydistinct/stats_estimators.py
pydistinct/test.py
pydistinct/utils.py
pydistinct-0.6.4.dist-info/DESCRIPTION.rst
pydistinct-0.6.4.dist-info/METADATA
pydistinct-0.6.4.dist-info/RECORD
pydistinct-0.6.4.dist-info/WHEEL
pydistinct-0.6.4.dist-info/metadata.json
pydistinct-0.6.4.dist-info/top_level.txt
