Metadata-Version: 2.0
Name: pydistinct
Version: 0.6.4
Summary: Package for estimating distinct values in a population
Home-page: https://github.com/chanedwin/pydistinct/
Author: Edwin Chan
Author-email: edwinchan@u.nus.edu
License: UNKNOWN
Download-URL: https://github.com/chanedwin/pydistinct/archive/0.5.tar.gz
Keywords: distinct,value,estimators,sample,sequences
Platform: UNKNOWN
Classifier: Programming Language :: Python :: 3
Classifier: License :: OSI Approved :: MIT License
Classifier: Operating System :: OS Independent
Requires-Dist: scipy
Requires-Dist: statsmodels
Requires-Dist: xgboost
Requires-Dist: numpy
Requires-Dist: m2r
